{
	"configurations" : 
	[
		{
			"directories" : 
			[
				{
					"build" : ".",
					"jsonFile" : "directory-.-Debug-f5ebdc15457944623624.json",
					"minimumCMakeVersion" : 
					{
						"string" : "3.12"
					},
					"projectIndex" : 0,
					"source" : ".",
					"targetIndexes" : 
					[
						0,
						1,
						2,
						3,
						4,
						5,
						6
					]
				}
			],
			"name" : "Debug",
			"projects" : 
			[
				{
					"directoryIndexes" : 
					[
						0
					],
					"name" : "FileSystem",
					"targetIndexes" : 
					[
						0,
						1,
						2,
						3,
						4,
						5,
						6
					]
				}
			],
			"targets" : 
			[
				{
					"directoryIndex" : 0,
					"id" : "cleanBuild::@6890427a1f51a3e7e1df",
					"jsonFile" : "target-cleanBuild-Debug-7ea2485dbc8dabe3f4fb.json",
					"name" : "cleanBuild",
					"projectIndex" : 0
				},
				{
					"directoryIndex" : 0,
					"id" : "filesystem::@6890427a1f51a3e7e1df",
					"jsonFile" : "target-filesystem-Debug-45a217dca3661670b16a.json",
					"name" : "filesystem",
					"projectIndex" : 0
				},
				{
					"directoryIndex" : 0,
					"id" : "test1::@6890427a1f51a3e7e1df",
					"jsonFile" : "target-test1-Debug-93a78e0ae0d92432b91b.json",
					"name" : "test1",
					"projectIndex" : 0
				},
				{
					"directoryIndex" : 0,
					"id" : "test2::@6890427a1f51a3e7e1df",
					"jsonFile" : "target-test2-Debug-1bbc7aca1f85154ac319.json",
					"name" : "test2",
					"projectIndex" : 0
				},
				{
					"directoryIndex" : 0,
					"id" : "test3::@6890427a1f51a3e7e1df",
					"jsonFile" : "target-test3-Debug-f512378f81e3f4d10568.json",
					"name" : "test3",
					"projectIndex" : 0
				},
				{
					"directoryIndex" : 0,
					"id" : "test4::@6890427a1f51a3e7e1df",
					"jsonFile" : "target-test4-Debug-ac485212e7775b5e3138.json",
					"name" : "test4",
					"projectIndex" : 0
				},
				{
					"directoryIndex" : 0,
					"id" : "test5::@6890427a1f51a3e7e1df",
					"jsonFile" : "target-test5-Debug-43304f061fb3febda063.json",
					"name" : "test5",
					"projectIndex" : 0
				}
			]
		}
	],
	"kind" : "codemodel",
	"paths" : 
	{
		"build" : "/home/skyh1gh/Desktop/Skolprojekt/Operativsystem/Lab 3/cmake-build-debug",
		"source" : "/home/skyh1gh/Desktop/Skolprojekt/Operativsystem/Lab 3"
	},
	"version" : 
	{
		"major" : 2,
		"minor" : 6
	}
}
